tensordash/__init__.py
tensordash/gqlOperations.py
tensordash/main.py
tensordash-0.1.0.dist-info/METADATA
tensordash-0.1.0.dist-info/WHEEL
tensordash-0.1.0.dist-info/entry_points.txt
tensordash-0.1.0.dist-info/top_level.txt
tensordash-0.1.0.dist-info/RECORD
