Metadata-Version: 2.1
Name: tensordash
Version: 0.1.0
Summary: A dashboard for your AI experiments
Home-page: https://github.com/tensordash/tensordash
Author: tensordash
Author-email: info@tensordash.ai
License: UNKNOWN
Platform: UNKNOWN
Requires-Dist: six
Requires-Dist: warrant
Requires-Dist: gql
Requires-Dist: requests
